{"name":"Searching a dress with at less three diamonds","id":"alibaba-search;searching-a-dress-with-at-less-three-diamonds","testSteps":[{"number":1,"description":"Example #1: {product\u003dblue dress, email\u003dand-rua@hotmail.com, detail\u003dHave_you_descount?}","duration":33977,"startTime":"2018-11-23T19:43:51.074-05:00[America/Bogota]","screenshots":[{"screenshot":"8f7fb7b53a254801a87a25d7cb5bc529e7c71ef9af79b31003c79522d1025531.png"}],"result":"SUCCESS","precondition":false,"children":[{"number":2,"description":"Given I into Alibaba","duration":12582,"startTime":"2018-11-23T19:43:51.221-05:00[America/Bogota]","screenshots":[{"screenshot":"69eee465ef498dad69ed4d583066e6b67a1b7737ff63a2a9fcc27fe29e3abaff.png"}],"result":"SUCCESS","precondition":false,"children":[{"number":3,"description":"andres opens the Alibaba home page","duration":11669,"startTime":"2018-11-23T19:43:51.633-05:00[America/Bogota]","screenshots":[{"screenshot":"69eee465ef498dad69ed4d583066e6b67a1b7737ff63a2a9fcc27fe29e3abaff.png"}],"result":"SUCCESS","precondition":false}]},{"number":4,"description":"When I search for an article blue dress","duration":8434,"startTime":"2018-11-23T19:44:03.804-05:00[America/Bogota]","screenshots":[{"screenshot":"b8ec60834fc96b594195df10694687e2e04ed78257a600cb141b6c4343ee53ee.png"},{"screenshot":"48d5812a63162fdd70644ac8c77ea8b444ff6e8d8c761885455fc6c864553d5f.png"}],"result":"SUCCESS","precondition":false,"children":[{"number":5,"description":"andres enters \u0027blue dress\u0027 into Source search text area","duration":1289,"startTime":"2018-11-23T19:44:04.350-05:00[America/Bogota]","screenshots":[{"screenshot":"88663e996f3d03e6ac1700b36eb2d6648f00e0883773b6828465614156f8d63d.png"},{"screenshot":"f70d5cd7e5c1bb5b7a679dd7d6e8ab5ef4d240e08d28333db29098a1e867c447.png"}],"result":"SUCCESS","precondition":false},{"number":6,"description":"andres clicks on Source button","duration":5318,"startTime":"2018-11-23T19:44:05.653-05:00[America/Bogota]","screenshots":[{"screenshot":"4fc0d4027d34db1aa11f5aba54768e336852bdc16a12330371aeea5a57753575.png"},{"screenshot":"0030378ea88111780a448c1d953e1ab7245b1c28d634dc2d039780d7a6c20a29.png"}],"result":"SUCCESS","precondition":false}]},{"number":7,"description":"And find some with at less diamonds","duration":4436,"startTime":"2018-11-23T19:44:12.238-05:00[America/Bogota]","screenshots":[{"screenshot":"8e7f84843e0392fd5e6d048c2b6841fa19400c5eb99aa2881e444702cc89885a.png"},{"screenshot":"7cc0226b935a61d45be49c5c60f824c9fc8896e88a993891cc4ee65a95b47821.png"}],"result":"SUCCESS","precondition":false,"children":[{"number":8,"description":"andres clicks on Product","duration":1901,"startTime":"2018-11-23T19:44:12.679-05:00[America/Bogota]","screenshots":[{"screenshot":"8e7f84843e0392fd5e6d048c2b6841fa19400c5eb99aa2881e444702cc89885a.png"},{"screenshot":"d3694d521209244ecfa2fc3f8cce657aa9ebb4244761b5581eb584456193b60e.png"}],"result":"SUCCESS","precondition":false}]},{"number":9,"description":"When contact with supplier and-rua@hotmail.com Have_you_descount?","duration":7510,"startTime":"2018-11-23T19:44:16.675-05:00[America/Bogota]","screenshots":[{"screenshot":"004f2f1a6ffb39b68543dca8609b39721efba5bc4b2a5bb83a4fb37ab5cdb33c.png"},{"screenshot":"8f7fb7b53a254801a87a25d7cb5bc529e7c71ef9af79b31003c79522d1025531.png"}],"result":"SUCCESS","precondition":false,"children":[{"number":10,"description":"andres clicks on Product Contact","duration":3827,"startTime":"2018-11-23T19:44:17.276-05:00[America/Bogota]","screenshots":[{"screenshot":"7b367a07cbb91420bf25820cb00109e0fd19fbfb892506887a7dde99e276fc2b.png"},{"screenshot":"86f9cb1a1fbc02ac0f741b07b3df27c5b94bc368993583721c14917d43234aeb.png"}],"result":"SUCCESS","precondition":false},{"number":11,"description":"andres enters \u0027100\u0027 into Quantity","duration":920,"startTime":"2018-11-23T19:44:21.108-05:00[America/Bogota]","screenshots":[{"screenshot":"86f9cb1a1fbc02ac0f741b07b3df27c5b94bc368993583721c14917d43234aeb.png"},{"screenshot":"53e7b5730cc7ad3cb07c3bad54228529ba4f95ca16a1fdd1d4225b14714556db.png"}],"result":"SUCCESS","precondition":false},{"number":12,"description":"andres enters \u0027and-rua@hotmail.com\u0027 into Email","duration":964,"startTime":"2018-11-23T19:44:22.033-05:00[America/Bogota]","screenshots":[{"screenshot":"802a253f2196bf15e4c00254c8da8800939b02a2fa67bd67936af884844c5763.png"},{"screenshot":"3b0bc3e7c61114cfbfc61706e60294c86debd8d2f627020b2d052f6a21761cb7.png"}],"result":"SUCCESS","precondition":false},{"number":13,"description":"andres enters \u0027Have_you_descount?\u0027 into Details","duration":903,"startTime":"2018-11-23T19:44:23.005-05:00[America/Bogota]","screenshots":[{"screenshot":"b5f6a8efb7a0afde33703a8ba491d75d2afae9b1a013da1b29a7c7c1c67c92a8.png"},{"screenshot":"8f7fb7b53a254801a87a25d7cb5bc529e7c71ef9af79b31003c79522d1025531.png"}],"result":"SUCCESS","precondition":false}]},{"number":14,"description":"Then I validate the outcomes","duration":534,"startTime":"2018-11-23T19:44:24.186-05:00[America/Bogota]","screenshots":[{"screenshot":"5279a5e0ae17f603ce3831f9b92d91ac32beffa804a71d4caab8b90a974aa22c.png"}],"result":"SUCCESS","precondition":false}]}],"userStory":{"id":"alibaba-search","storyName":"Alibaba search","path":"src/test/resources/features/Alibaba.feature","narrative":"  I want to make a search in alibaba","type":"feature"},"featureTag":{"name":"Features/Alibaba search","type":"feature"},"title":"Searching a dress with at less three diamonds","tags":[{"name":"tag1","type":"tag"},{"name":"tag","type":"tag"},{"name":"Alibaba search","type":"feature"}],"startTime":"2018-11-23T19:43:50.695-05:00[America/Bogota]","duration":34357,"projectKey":"","sessionId":"441e25a4892d71bcd6c8bc2b4d80d5b5","driver":"chrome","dataTable":{"headers":["product","email","detail"],"rows":[{"values":["blue dress","and-rua@hotmail.com","Have_you_descount?"],"result":"SUCCESS"}],"predefinedRows":true,"scenarioOutline":"Given I into Alibaba\n\rWhen I search for an article \u003cproduct\u003e\n\rAnd find some with at less diamonds\n\rWhen contact with supplier \u003cemail\u003e \u003cdetail\u003e\n\rThen I validate the outcomes\n\r","dataSetDescriptors":[{"startRow":0,"rowCount":0,"name":""}]},"manual":false,"testSource":"Cucumber","actors":[{"name":"andres","can":["browse the web with FIREFOX"]}],"result":"SUCCESS","scenarioOutline":"Given I into Alibaba\r\nWhen I search for an article \u003cproduct\u003e\r\nAnd find some with at less diamonds\r\nWhen contact with supplier \u003cemail\u003e \u003cdetail\u003e\r\nThen I validate the outcomes"}